DepyTG-4.0.0.dist-info/METADATA
DepyTG-4.0.0.dist-info/RECORD
DepyTG-4.0.0.dist-info/WHEEL
DepyTG-4.0.0.dist-info/top_level.txt
depytg/__init__.py
depytg/depyfier.py
depytg/errors.py
depytg/internals.py
depytg/methods.py
depytg/types.py
depytg/utils.py
depytg/webhooks/__init__.py
depytg/webhooks/flask.py
