Metadata-Version: 2.1
Name: DepyTG
Version: 4.0.0
Summary: The only Telegram bot library that does nothing
Home-page: https://github.com/Depau/DepyTG
Author: Davide Depau
Author-email: davide@depau.eu
License: MIT
Keywords: telegram bot development
Platform: UNKNOWN
Classifier: Development Status :: 4 - Beta
Classifier: License :: OSI Approved :: MIT License
Classifier: Programming Language :: Python
Classifier: Programming Language :: Python :: 3
Classifier: Programming Language :: Python :: 3.6
Classifier: Programming Language :: Python :: 3.7
Classifier: Programming Language :: Python :: 3 :: Only
Classifier: Topic :: Communications :: Chat
Classifier: Intended Audience :: Developers
Classifier: Topic :: Software Development :: Libraries
Classifier: Topic :: Software Development :: Libraries :: Python Modules
Requires-Python: >=3
Provides-Extra: asyncio
Provides-Extra: flask
Requires-Dist: requests
Requires-Dist: asyncio
Provides-Extra: asyncio
Requires-Dist: aiohttp; extra == 'asyncio'
Provides-Extra: flask
Requires-Dist: Flask; extra == 'flask'
